pandaswizard/__init__.py
pandaswizard/aggregate.py
pandaswizard/window.py
pandaswizard/wrappers.py
pandaswizard/functions/__init__.py
pandaswizard/functions/collate.py
pandas_wizard-1.1.0.dist-info/LICENSE
pandas_wizard-1.1.0.dist-info/METADATA
pandas_wizard-1.1.0.dist-info/WHEEL
pandas_wizard-1.1.0.dist-info/top_level.txt
pandas_wizard-1.1.0.dist-info/RECORD
