Metadata-Version: 2.1
Name: pandas-wizard
Version: 1.1.0
Summary: Utility Functions, Wrappers for pandas Module
Home-page: https://github.com/sharkutilities/pandas-wizard
Author: shark-utilities developers
Author-email: sharkutilities <neuralNOD@outlook.com>
License: MIT License        
Project-URL: Homepage, https://github.com/sharkutilities/pandas-wizard
Project-URL: Documentation, https://pandas-wizard.readthedocs.io/en/latest/index.html
Project-URL: Issues, https://github.com/sharkutilities/pandas-wizard/issues
Project-URL: Changelog, https://github.com/sharkutilities/pandas-wizard/blob/master/CHANGELOG.md
Keywords: pandas,utility,utilities,util,utils,wrappers,data science,data analysis,data scientist,data analyst,statistics,percentile,quantile,probability
Classifier: Development Status :: 1 - Planning
Classifier: Intended Audience :: Developers
Classifier: Intended Audience :: Education
Classifier: Intended Audience :: End Users/Desktop
Classifier: Intended Audience :: Information Technology
Classifier: Intended Audience :: Science/Research
Classifier: Operating System :: Unix
Classifier: Operating System :: POSIX
Classifier: Operating System :: Microsoft :: Windows
Classifier: Programming Language :: Python
Classifier: Programming Language :: Python :: 3
Classifier: Programming Language :: Python :: 3 :: Only
Classifier: Programming Language :: Python :: 3.8
Classifier: Programming Language :: Python :: 3.9
Classifier: Programming Language :: Python :: 3.10
Classifier: Programming Language :: Python :: 3.11
Classifier: Programming Language :: Python :: 3.12
Classifier: License :: OSI Approved :: MIT License
Requires-Python: >=3.8
License-File: LICENSE
